getit/__init__.py
getit/getit.py
getit-2.2.dist-info/DESCRIPTION.rst
getit-2.2.dist-info/METADATA
getit-2.2.dist-info/RECORD
getit-2.2.dist-info/WHEEL
getit-2.2.dist-info/entry_points.txt
getit-2.2.dist-info/metadata.json
getit-2.2.dist-info/top_level.txt
