Metadata-Version: 2.0
Name: getit
Version: 2.2
Summary: A cross platform CLI downloader tool written in python.
Home-page: https://github.com/ankitjain28may/getit
Author: Ankit Jain
Author-email: ankitjain28may77@gmail.com
License: MIT
Keywords: download cli,downloaded-tool,cross-platform-cli-downloader
Platform: UNKNOWN
Classifier: Development Status :: 3 - Alpha
Classifier: Environment :: Console
Classifier: Intended Audience :: Developers
Classifier: Intended Audience :: Information Technology
Classifier: Natural Language :: English
Classifier: Topic :: Software Development :: Build Tools
Classifier: License :: OSI Approved :: MIT License
Classifier: Programming Language :: Python :: 3
Classifier: Programming Language :: Python :: 3.3
Classifier: Programming Language :: Python :: 3.4
Classifier: Programming Language :: Python :: 3.5
Requires-Dist: colorama (>=0.3.7)
Requires-Dist: configparser (>=3.5.0)
Requires-Dist: requests (==2.10.0)
